LinguaLover/__init__.py
LinguaLover/message.py
LinguaLover/utils.py
LinguaLover-1.0.0.dist-info/LICENSE
LinguaLover-1.0.0.dist-info/METADATA
LinguaLover-1.0.0.dist-info/WHEEL
LinguaLover-1.0.0.dist-info/top_level.txt
LinguaLover-1.0.0.dist-info/RECORD
