Metadata-Version: 2.1
Name: LinguaLover
Version: 1.0.0
Summary: A library to say your love.
Home-page: https://github.com/emirkaanozdemr/iloveyou
Author: Emir Kaan Özdemir
Author-email: emirkaanbulut08@gmail.com
License: Apache License 2.0
Classifier: Programming Language :: Python :: 3
Classifier: License :: OSI Approved :: Apache Software License
Classifier: Operating System :: OS Independent
Requires-Python: >=3.6
License-File: LICENSE
